{"DEVIR":[],"GENEXP1":[],"GENEXP2":[],"REPORTRATE":[],"NETTOTAL":[],"GENEXP3":[],"GENEXP4":[],"TRACKNR":[],"PRODORDERREF":[],"FICHENO":[],"VAACCREF":[],"INUSE":[],"ACCFICHEREF":[],"SENDCNT":[],"CANCELLEDACC":[],"FTIME":[],"IOCODE":[],"DLVCLIENT":[],"GENEXCTYP":[],"TOTALEXPENSES":[],"CAPIBLOCK_MODIFIEDHOUR":[],"SHIPINFOREF":[],"DEPARTMENT":[],"BILLED":[],"VACENTERREF":[],"WFLOWCRDREF":[],"COMPBRANCH":[],"TEXTINC":[],"SOURCEWSREF":[],"CYPHCODE":[],"UGIRTRACKINGNO":[],"TRCURR":[],"ACCOUNTREF":[],"CAPIBLOCK_MODIFIEDDATE":[],"CLIENTREF":[],"GROSSTOTAL":[],"DESTINDEX":[],"EXIMWHFCREF":[],"WFSTATUS":[],"RECSTATUS":[],"EXIMFCTYPE":[],"ACCOUNTED":[],"TRRATE":[],"SPECODE":[],"FROMORDWITHPAY":[],"PAYDEFREF":[],"UPDCURR":[],"CAPIBLOCK_MODIFIEDMIN":[],"SOURCETYPE":[],"SITEID":[],"TOTALEXADDTAX":[],"TRADINGGRP":[],"AFFECTRISK":[],"SALESMANREF":[],"COMPDEPARTMENT":[],"CAPIBLOCK_CREADEDDATE":[],"MAINSTFCREF":[],"DOCODE":[],"INVKIND":[],"INVNO":[],"SOURCECOSTGRP":[],"GRPCODE":[],"DESTWSREF":[],"ORGLOGICREF":[],"DESTPOLNREF":[],"CAPIBLOCK_MODIFIEDBY":[],"ORGLOGOID":[],"DESTCOSTGRP":[],"TRCODE":[],"DEDUCTIONPART1":[],"STATUS":[],"DEDUCTIONPART2":[],"CAPIBLOCK_MODIFIEDSEC":[],"ADDEXPENSES":[],"INVOICEREF":[],"RECVREF":[],"TOTALVAT":[],"DESTTYPE":[],"TOTALDISCOUNTED":[],"QPRODFCREF":[],"SHPAGNCOD":[],"PROJECTREF":[],"SOURCEINDEX":[],"CAPIBLOCK_CREATEDHOUR":[],"GRPFIRMTRANS":[],"DATE_":[],"ADDTAXCALC":[],"AFFECTCOLLATRL":[],"PORDERFICHENO":[],"CANCELLED":[],"SHPTYPCOD":[],"TOTALDISCOUNTS":[],"CAPIBLOCK_CREATEDBY":[],"FROMEXIM":[],"PRINTCNT":[],"REPORTNET":[],"UPDTRCURR":[],"DOCTRACKINGNR":[],"CAPIBLOCK_CREATEDMIN":[],"CAPIBLOCK_CREATEDSEC":[],"DISTORDERREF":[],"TOTALPROMOTIONS":[],"EXTENREF":[],"FACTORYNR":[],"COMPFACTORY":[],"FRGTYPCOD":[],"LINEEXCTYP":[],"BRANCH":[],"SOURCEPOLNREF":[],"FICHECNT":[],"ADDDISCOUNTS":[],"CENTERREF":[],"TOTALADDTAX":[],"LOGICALREF":[],"TOTALDEPOZITO":[],"TRNET":[],"PRODSTAT":[]}